Workbook

Sheet Mug Marks
A1: Mug Marks - Target Tracker
A2: Type only in blue columns (A-I, U). Everything else is automatic from the Mug Log. Times are TCT unless labelled Local.
A4: Target Name | B4: Torn ID | C4: Level | D4: Est. Total Stats | E4: Job | F4: Property | G4: Net Worth ($) | H4: Pipeline | I4: Days Inactive | J4: Profile | K4: Attack | L4: Last Mug (TCT) | M4: Last Yield ($) | N4: Next Available (TCT) | O4: Next Available (Local) | P4: Status | Q4: Ready In (h:mm) | R4: Hits | S4: Lifetime Yield ($) | T4: Avg Yield ($) | U4: Notes
A5: EXAMPLE Target (delete) | B5: 123456 | C5: 45 | D5: 500000 | E5: Brain Surgeon | F5: Private Island | G5: 6000000000 | H5: HoF Inactive | I5: 4 | J5: =IF(B5="","",HYPERLINK("https://www.torn.com/profiles.php?XID="&B5,"Profile")) -> Profile | K5: =IF(B5="","",HYPERLINK("https://www.torn.com/loader.php?sid=attack&user2ID="&B5,"Attack")) -> Attack | L5: =IF(B5="","",IF(COUNTIF('Mug Log'!$B$5:$B$1004,B5)=0,"",_xlfn.MAXIFS('Mug Log'!$A$5:$A$1004,'Mug Log'!$B$5:$B$1004,B5))) -> 46305.646 | M5: =IF(L5="","",SUMIFS('Mug Log'!$D$5:$D$1004,'Mug Log'!$B$5:$B$1004,B5,'Mug Log'!$A$5:$A$1004,L5)) -> 2400000 | N5: =IF(L5="","",L5+Settings!$B$7/24) -> 46306.271 | O5: =IF(N5="","",N5+Settings!$B$6/24) -> 46305.979 | P5: =IF(B5="","",IF(L5="","Never hit",IF(N5<=Settings!$B$8,"READY","Cooldown"))) -> Cooldown | Q5: =IF(P5="Cooldown",N5-Settings!$B$8,"") -> 0.0095575947 | R5: =IF(B5="","",COUNTIF('Mug Log'!$B$5:$B$1004,B5)) -> 1 | S5: =IF(B5="","",SUMIFS('Mug Log'!$D$5:$D$1004,'Mug Log'!$B$5:$B$1004,B5)) -> 2400000 | T5: =IF(OR(B5="",R5=0),"",S5/R5) -> 2400000 | U5: Inactive 4 days. Easy 2-hit kill. No mask worn.
J6: =IF(B6="","",HYPERLINK("https://www.torn.com/profiles.php?XID="&B6,"Profile")) | K6: =IF(B6="","",HYPERLINK("https://www.torn.com/loader.php?sid=attack&user2ID="&B6,"Attack")) | L6: =IF(B6="","",IF(COUNTIF('Mug Log'!$B$5:$B$1004,B6)=0,"",_xlfn.MAXIFS('Mug Log'!$A$5:$A$1004,'Mug Log'!$B$5:$B$1004,B6))) | M6: =IF(L6="","",SUMIFS('Mug Log'!$D$5:$D$1004,'Mug Log'!$B$5:$B$1004,B6,'Mug Log'!$A$5:$A$1004,L6)) | N6: =IF(L6="","",L6+Settings!$B$7/24) | O6: =IF(N6="","",N6+Settings!$B$6/24) | P6: =IF(B6="","",IF(L6="","Never hit",IF(N6<=Settings!$B$8,"READY","Cooldown"))) | Q6: =IF(P6="Cooldown",N6-Settings!$B$8,"") | R6: =IF(B6="","",COUNTIF('Mug Log'!$B$5:$B$1004,B6)) | S6: =IF(B6="","",SUMIFS('Mug Log'!$D$5:$D$1004,'Mug Log'!$B$5:$B$1004,B6)) | T6: =IF(OR(B6="",R6=0),"",S6/R6)
J7: =IF(B7="","",HYPERLINK("https://www.torn.com/profiles.php?XID="&B7,"Profile")) | K7: =IF(B7="","",HYPERLINK("https://www.torn.com/loader.php?sid=attack&user2ID="&B7,"Attack")) | L7: =IF(B7="","",IF(COUNTIF('Mug Log'!$B$5:$B$1004,B7)=0,"",_xlfn.MAXIFS('Mug Log'!$A$5:$A$1004,'Mug Log'!$B$5:$B$1004,B7))) | M7: =IF(L7="","",SUMIFS('Mug Log'!$D$5:$D$1004,'Mug Log'!$B$5:$B$1004,B7,'Mug Log'!$A$5:$A$1004,L7)) | N7: =IF(L7="","",L7+Settings!$B$7/24) | O7: =IF(N7="","",N7+Settings!$B$6/24) | P7: =IF(B7="","",IF(L7="","Never hit",IF(N7<=Settings!$B$8,"READY","Cooldown"))) | Q7: =IF(P7="Cooldown",N7-Settings!$B$8,"") | R7: =IF(B7="","",COUNTIF('Mug Log'!$B$5:$B$1004,B7)) | S7: =IF(B7="","",SUMIFS('Mug Log'!$D$5:$D$1004,'Mug Log'!$B$5:$B$1004,B7)) | T7: =IF(OR(B7="",R7=0),"",S7/R7)
J8: =IF(B8="","",HYPERLINK("https://www.torn.com/profiles.php?XID="&B8,"Profile")) | K8: =IF(B8="","",HYPERLINK("https://www.torn.com/loader.php?sid=attack&user2ID="&B8,"Attack")) | L8: =IF(B8="","",IF(COUNTIF('Mug Log'!$B$5:$B$1004,B8)=0,"",_xlfn.MAXIFS('Mug Log'!$A$5:$A$1004,'Mug Log'!$B$5:$B$1004,B8))) | M8: =IF(L8="","",SUMIFS('Mug Log'!$D$5:$D$1004,'Mug Log'!$B$5:$B$1004,B8,'Mug Log'!$A$5:$A$1004,L8)) | N8: =IF(L8="","",L8+Settings!$B$7/24) | O8: =IF(N8="","",N8+Settings!$B$6/24) | P8: =IF(B8="","",IF(L8="","Never hit",IF(N8<=Settings!$B$8,"READY","Cooldown"))) | Q8: =IF(P8="Cooldown",N8-Settings!$B$8,"") | R8: =IF(B8="","",COUNTIF('Mug Log'!$B$5:$B$1004,B8)) | S8: =IF(B8="","",SUMIFS('Mug Log'!$D$5:$D$1004,'Mug Log'!$B$5:$B$1004,B8)) | T8: =IF(OR(B8="",R8=0),"",S8/R8)
J9: =IF(B9="","",HYPERLINK("https://www.torn.com/profiles.php?XID="&B9,"Profile")) | K9: =IF(B9="","",HYPERLINK("https://www.torn.com/loader.php?sid=attack&user2ID="&B9,"Attack")) | L9: =IF(B9="","",IF(COUNTIF('Mug Log'!$B$5:$B$1004,B9)=0,"",_xlfn.MAXIFS('Mug Log'!$A$5:$A$1004,'Mug Log'!$B$5:$B$1004,B9))) | M9: =IF(L9="","",SUMIFS('Mug Log'!$D$5:$D$1004,'Mug Log'!$B$5:$B$1004,B9,'Mug Log'!$A$5:$A$1004,L9)) | N9: =IF(L9="","",L9+Settings!$B$7/24) | O9: =IF(N9="","",N9+Settings!$B$6/24) | P9: =IF(B9="","",IF(L9="","Never hit",IF(N9<=Settings!$B$8,"READY","Cooldown"))) | Q9: =IF(P9="Cooldown",N9-Settings!$B$8,"") | R9: =IF(B9="","",COUNTIF('Mug Log'!$B$5:$B$1004,B9)) | S9: =IF(B9="","",SUMIFS('Mug Log'!$D$5:$D$1004,'Mug Log'!$B$5:$B$1004,B9)) | T9: =IF(OR(B9="",R9=0),"",S9/R9)
J10: =IF(B10="","",HYPERLINK("https://www.torn.com/profiles.php?XID="&B10,"Profile")) | K10: =IF(B10="","",HYPERLINK("https://www.torn.com/loader.php?sid=attack&user2ID="&B10,"Attack")) | L10: =IF(B10="","",IF(COUNTIF('Mug Log'!$B$5:$B$1004,B10)=0,"",_xlfn.MAXIFS('Mug Log'!$A$5:$A$1004,'Mug Log'!$B$5:$B$1004,B10))) | M10: =IF(L10="","",SUMIFS('Mug Log'!$D$5:$D$1004,'Mug Log'!$B$5:$B$1004,B10,'Mug Log'!$A$5:$A$1004,L10)) | N10: =IF(L10="","",L10+Settings!$B$7/24) | O10: =IF(N10="","",N10+Settings!$B$6/24) | P10: =IF(B10="","",IF(L10="","Never hit",IF(N10<=Settings!$B$8,"READY","Cooldown"))) | Q10: =IF(P10="Cooldown",N10-Settings!$B$8,"") | R10: =IF(B10="","",COUNTIF('Mug Log'!$B$5:$B$1004,B10)) | S10: =IF(B10="","",SUMIFS('Mug Log'!$D$5:$D$1004,'Mug Log'!$B$5:$B$1004,B10)) | T10: =IF(OR(B10="",R10=0),"",S10/R10)
J11: =IF(B11="","",HYPERLINK("https://www.torn.com/profiles.php?XID="&B11,"Profile")) | K11: =IF(B11="","",HYPERLINK("https://www.torn.com/loader.php?sid=attack&user2ID="&B11,"Attack")) | L11: =IF(B11="","",IF(COUNTIF('Mug Log'!$B$5:$B$1004,B11)=0,"",_xlfn.MAXIFS('Mug Log'!$A$5:$A$1004,'Mug Log'!$B$5:$B$1004,B11))) | M11: =IF(L11="","",SUMIFS('Mug Log'!$D$5:$D$1004,'Mug Log'!$B$5:$B$1004,B11,'Mug Log'!$A$5:$A$1004,L11)) | N11: =IF(L11="","",L11+Settings!$B$7/24) | O11: =IF(N11="","",N11+Settings!$B$6/24) | P11: =IF(B11="","",IF(L11="","Never hit",IF(N11<=Settings!$B$8,"READY","Cooldown"))) | Q11: =IF(P11="Cooldown",N11-Settings!$B$8,"") | R11: =IF(B11="","",COUNTIF('Mug Log'!$B$5:$B$1004,B11)) | S11: =IF(B11="","",SUMIFS('Mug Log'!$D$5:$D$1004,'Mug Log'!$B$5:$B$1004,B11)) | T11: =IF(OR(B11="",R11=0),"",S11/R11)
J12: =IF(B12="","",HYPERLINK("https://www.torn.com/profiles.php?XID="&B12,"Profile")) | K12: =IF(B12="","",HYPERLINK("https://www.torn.com/loader.php?sid=attack&user2ID="&B12,"Attack")) | L12: =IF(B12="","",IF(COUNTIF('Mug Log'!$B$5:$B$1004,B12)=0,"",_xlfn.MAXIFS('Mug Log'!$A$5:$A$1004,'Mug Log'!$B$5:$B$1004,B12))) | M12: =IF(L12="","",SUMIFS('Mug Log'!$D$5:$D$1004,'Mug Log'!$B$5:$B$1004,B12,'Mug Log'!$A$5:$A$1004,L12)) | N12: =IF(L12="","",L12+Settings!$B$7/24) | O12: =IF(N12="","",N12+Settings!$B$6/24) | P12: =IF(B12="","",IF(L12="","Never hit",IF(N12<=Settings!$B$8,"READY","Cooldown"))) | Q12: =IF(P12="Cooldown",N12-Settings!$B$8,"") | R12: =IF(B12="","",COUNTIF('Mug Log'!$B$5:$B$1004,B12)) | S12: =IF(B12="","",SUMIFS('Mug Log'!$D$5:$D$1004,'Mug Log'!$B$5:$B$1004,B12)) | T12: =IF(OR(B12="",R12=0),"",S12/R12)
J13: =IF(B13="","",HYPERLINK("https://www.torn.com/profiles.php?XID="&B13,"Profile")) | K13: =IF(B13="","",HYPERLINK("https://www.torn.com/loader.php?sid=attack&user2ID="&B13,"Attack")) | L13: =IF(B13="","",IF(COUNTIF('Mug Log'!$B$5:$B$1004,B13)=0,"",_xlfn.MAXIFS('Mug Log'!$A$5:$A$1004,'Mug Log'!$B$5:$B$1004,B13))) | M13: =IF(L13="","",SUMIFS('Mug Log'!$D$5:$D$1004,'Mug Log'!$B$5:$B$1004,B13,'Mug Log'!$A$5:$A$1004,L13)) | N13: =IF(L13="","",L13+Settings!$B$7/24) | O13: =IF(N13="","",N13+Settings!$B$6/24) | P13: =IF(B13="","",IF(L13="","Never hit",IF(N13<=Settings!$B$8,"READY","Cooldown"))) | Q13: =IF(P13="Cooldown",N13-Settings!$B$8,"") | R13: =IF(B13="","",COUNTIF('Mug Log'!$B$5:$B$1004,B13)) | S13: =IF(B13="","",SUMIFS('Mug Log'!$D$5:$D$1004,'Mug Log'!$B$5:$B$1004,B13)) | T13: =IF(OR(B13="",R13=0),"",S13/R13)
J14: =IF(B14="","",HYPERLINK("https://www.torn.com/profiles.php?XID="&B14,"Profile")) | K14: =IF(B14="","",HYPERLINK("https://www.torn.com/loader.php?sid=attack&user2ID="&B14,"Attack")) | L14: =IF(B14="","",IF(COUNTIF('Mug Log'!$B$5:$B$1004,B14)=0,"",_xlfn.MAXIFS('Mug Log'!$A$5:$A$1004,'Mug Log'!$B$5:$B$1004,B14))) | M14: =IF(L14="","",SUMIFS('Mug Log'!$D$5:$D$1004,'Mug Log'!$B$5:$B$1004,B14,'Mug Log'!$A$5:$A$1004,L14)) | N14: =IF(L14="","",L14+Settings!$B$7/24) | O14: =IF(N14="","",N14+Settings!$B$6/24) | P14: =IF(B14="","",IF(L14="","Never hit",IF(N14<=Settings!$B$8,"READY","Cooldown"))) | Q14: =IF(P14="Cooldown",N14-Settings!$B$8,"") | R14: =IF(B14="","",COUNTIF('Mug Log'!$B$5:$B$1004,B14)) | S14: =IF(B14="","",SUMIFS('Mug Log'!$D$5:$D$1004,'Mug Log'!$B$5:$B$1004,B14)) | T14: =IF(OR(B14="",R14=0),"",S14/R14)
J15: =IF(B15="","",HYPERLINK("https://www.torn.com/profiles.php?XID="&B15,"Profile")) | K15: =IF(B15="","",HYPERLINK("https://www.torn.com/loader.php?sid=attack&user2ID="&B15,"Attack")) | L15: =IF(B15="","",IF(COUNTIF('Mug Log'!$B$5:$B$1004,B15)=0,"",_xlfn.MAXIFS('Mug Log'!$A$5:$A$1004,'Mug Log'!$B$5:$B$1004,B15))) | M15: =IF(L15="","",SUMIFS('Mug Log'!$D$5:$D$1004,'Mug Log'!$B$5:$B$1004,B15,'Mug Log'!$A$5:$A$1004,L15)) | N15: =IF(L15="","",L15+Settings!$B$7/24) | O15: =IF(N15="","",N15+Settings!$B$6/24) | P15: =IF(B15="","",IF(L15="","Never hit",IF(N15<=Settings!$B$8,"READY","Cooldown"))) | Q15: =IF(P15="Cooldown",N15-Settings!$B$8,"") | R15: =IF(B15="","",COUNTIF('Mug Log'!$B$5:$B$1004,B15)) | S15: =IF(B15="","",SUMIFS('Mug Log'!$D$5:$D$1004,'Mug Log'!$B$5:$B$1004,B15)) | T15: =IF(OR(B15="",R15=0),"",S15/R15)
J16: =IF(B16="","",HYPERLINK("https://www.torn.com/profiles.php?XID="&B16,"Profile")) | K16: =IF(B16="","",HYPERLINK("https://www.torn.com/loader.php?sid=attack&user2ID="&B16,"Attack")) | L16: =IF(B16="","",IF(COUNTIF('Mug Log'!$B$5:$B$1004,B16)=0,"",_xlfn.MAXIFS('Mug Log'!$A$5:$A$1004,'Mug Log'!$B$5:$B$1004,B16))) | M16: =IF(L16="","",SUMIFS('Mug Log'!$D$5:$D$1004,'Mug Log'!$B$5:$B$1004,B16,'Mug Log'!$A$5:$A$1004,L16)) | N16: =IF(L16="","",L16+Settings!$B$7/24) | O16: =IF(N16="","",N16+Settings!$B$6/24) | P16: =IF(B16="","",IF(L16="","Never hit",IF(N16<=Settings!$B$8,"READY","Cooldown"))) | Q16: =IF(P16="Cooldown",N16-Settings!$B$8,"") | R16: =IF(B16="","",COUNTIF('Mug Log'!$B$5:$B$1004,B16)) | S16: =IF(B16="","",SUMIFS('Mug Log'!$D$5:$D$1004,'Mug Log'!$B$5:$B$1004,B16)) | T16: =IF(OR(B16="",R16=0),"",S16/R16)
J17: =IF(B17="","",HYPERLINK("https://www.torn.com/profiles.php?XID="&B17,"Profile")) | K17: =IF(B17="","",HYPERLINK("https://www.torn.com/loader.php?sid=attack&user2ID="&B17,"Attack")) | L17: =IF(B17="","",IF(COUNTIF('Mug Log'!$B$5:$B$1004,B17)=0,"",_xlfn.MAXIFS('Mug Log'!$A$5:$A$1004,'Mug Log'!$B$5:$B$1004,B17))) | M17: =IF(L17="","",SUMIFS('Mug Log'!$D$5:$D$1004,'Mug Log'!$B$5:$B$1004,B17,'Mug Log'!$A$5:$A$1004,L17)) | N17: =IF(L17="","",L17+Settings!$B$7/24) | O17: =IF(N17="","",N17+Settings!$B$6/24) | P17: =IF(B17="","",IF(L17="","Never hit",IF(N17<=Settings!$B$8,"READY","Cooldown"))) | Q17: =IF(P17="Cooldown",N17-Settings!$B$8,"") | R17: =IF(B17="","",COUNTIF('Mug Log'!$B$5:$B$1004,B17)) | S17: =IF(B17="","",SUMIFS('Mug Log'!$D$5:$D$1004,'Mug Log'!$B$5:$B$1004,B17)) | T17: =IF(OR(B17="",R17=0),"",S17/R17)
... J204: =IF(B204="","",HYPERLINK("https://www.torn.com/profiles.php?XID="&B204,"Profile")) | K204: =IF(B204="","",HYPERLINK("https://www.torn.com/loader.php?sid=attack&user2ID="&B204,"Attack")) | L204: =IF(B204="","",IF(COUNTIF('Mug Log'!$B$5:$B$1004,B204)=0,"",_xlfn.MAXIFS('Mug Log'!$A$5:$A$1004,'Mug Log'!$B$5:$B$1004,B204))) | M204: =IF(L204="","",SUMIFS('Mug Log'!$D$5:$D$1004,'Mug Log'!$B$5:$B$1004,B204,'Mug Log'!$A$5:$A$1004,L204)) | N204: =IF(L204="","",L204+Settings!$B$7/24) | O204: =IF(N204="","",N204+Settings!$B$6/24) | P204: =IF(B204="","",IF(L204="","Never hit",IF(N204<=Settings!$B$8,"READY","Cooldown"))) | Q204: =IF(P204="Cooldown",N204-Settings!$B$8,"") | R204: =IF(B204="","",COUNTIF('Mug Log'!$B$5:$B$1004,B204)) | S204: =IF(B204="","",SUMIFS('Mug Log'!$D$5:$D$1004,'Mug Log'!$B$5:$B$1004,B204)) | T204: =IF(OR(B204="",R204=0),"",S204/R204)

Sheet Mug Log
A1: Mug Log
A2: One row per attack. Enter time in TCT (copy from Torn attack log). Name fills in automatically if the Torn ID exists on 'Mug Marks'.
A4: Time (TCT) | B4: Target Torn ID | C4: Target Name | D4: Cash Yield ($) | E4: Outcome | F4: Notes | G4: Time (Local)
A5: 46305.646 | B5: 123456 | C5: =IF(B5="","",IFERROR(INDEX('Mug Marks'!$A$5:$A$204,MATCH(B5,'Mug Marks'!$B$5:$B$204,0)),"(not on Mug Marks)")) -> EXAMPLE Target (delete) | D5: 2400000 | E5: Success | F5: EXAMPLE row (delete) - from your template | G5: =IF(A5="","",A5+Settings!$B$6/24) -> 46305.354
C6: =IF(B6="","",IFERROR(INDEX('Mug Marks'!$A$5:$A$204,MATCH(B6,'Mug Marks'!$B$5:$B$204,0)),"(not on Mug Marks)")) | G6: =IF(A6="","",A6+Settings!$B$6/24)
C7: =IF(B7="","",IFERROR(INDEX('Mug Marks'!$A$5:$A$204,MATCH(B7,'Mug Marks'!$B$5:$B$204,0)),"(not on Mug Marks)")) | G7: =IF(A7="","",A7+Settings!$B$6/24)
C8: =IF(B8="","",IFERROR(INDEX('Mug Marks'!$A$5:$A$204,MATCH(B8,'Mug Marks'!$B$5:$B$204,0)),"(not on Mug Marks)")) | G8: =IF(A8="","",A8+Settings!$B$6/24)
C9: =IF(B9="","",IFERROR(INDEX('Mug Marks'!$A$5:$A$204,MATCH(B9,'Mug Marks'!$B$5:$B$204,0)),"(not on Mug Marks)")) | G9: =IF(A9="","",A9+Settings!$B$6/24)
C10: =IF(B10="","",IFERROR(INDEX('Mug Marks'!$A$5:$A$204,MATCH(B10,'Mug Marks'!$B$5:$B$204,0)),"(not on Mug Marks)")) | G10: =IF(A10="","",A10+Settings!$B$6/24)
C11: =IF(B11="","",IFERROR(INDEX('Mug Marks'!$A$5:$A$204,MATCH(B11,'Mug Marks'!$B$5:$B$204,0)),"(not on Mug Marks)")) | G11: =IF(A11="","",A11+Settings!$B$6/24)
C12: =IF(B12="","",IFERROR(INDEX('Mug Marks'!$A$5:$A$204,MATCH(B12,'Mug Marks'!$B$5:$B$204,0)),"(not on Mug Marks)")) | G12: =IF(A12="","",A12+Settings!$B$6/24)
C13: =IF(B13="","",IFERROR(INDEX('Mug Marks'!$A$5:$A$204,MATCH(B13,'Mug Marks'!$B$5:$B$204,0)),"(not on Mug Marks)")) | G13: =IF(A13="","",A13+Settings!$B$6/24)
C14: =IF(B14="","",IFERROR(INDEX('Mug Marks'!$A$5:$A$204,MATCH(B14,'Mug Marks'!$B$5:$B$204,0)),"(not on Mug Marks)")) | G14: =IF(A14="","",A14+Settings!$B$6/24)
C15: =IF(B15="","",IFERROR(INDEX('Mug Marks'!$A$5:$A$204,MATCH(B15,'Mug Marks'!$B$5:$B$204,0)),"(not on Mug Marks)")) | G15: =IF(A15="","",A15+Settings!$B$6/24)
C16: =IF(B16="","",IFERROR(INDEX('Mug Marks'!$A$5:$A$204,MATCH(B16,'Mug Marks'!$B$5:$B$204,0)),"(not on Mug Marks)")) | G16: =IF(A16="","",A16+Settings!$B$6/24)
C17: =IF(B17="","",IFERROR(INDEX('Mug Marks'!$A$5:$A$204,MATCH(B17,'Mug Marks'!$B$5:$B$204,0)),"(not on Mug Marks)")) | G17: =IF(A17="","",A17+Settings!$B$6/24)
... C1004: =IF(B1004="","",IFERROR(INDEX('Mug Marks'!$A$5:$A$204,MATCH(B1004,'Mug Marks'!$B$5:$B$204,0)),"(not on Mug Marks)")) | G1004: =IF(A1004="","",A1004+Settings!$B$6/24)

Sheet Settings
A1: Settings & Summary
A2: Yellow cells are yours to edit. All times in the log are Torn City Time (TCT = UTC).
A4: Local UTC offset override (hrs) | C4: Leave blank to auto-detect. Use e.g. -8 for Pacific Standard, 0 for UTC.
A5: Auto-detected offset (US Pacific) | B5: =IF(AND(TODAY()>=DATE(YEAR(TODAY()),3,1)+MOD(8-WEEKDAY(DATE(YEAR(TODAY()),3,1)),7)+7,TODAY()<DATE(YEAR(TODAY()),11,1)+MOD(8-WEEKDAY(DATE(YEAR(TODAY()),11,1)),7)),-7,-8) -> -7 | C5: -7 during US daylight time (2nd Sun Mar - 1st Sun Nov), else -8. Pacific only.
A6: Effective local offset (hrs) | B6: =IF(B4<>"",B4,B5) -> -7 | C6: What the sheet actually uses.
A7: Mug cooldown (hours) | B7: 15 | C7: ASSUMPTION from your MuggingMarks.txt notes (unverified). Change here if you confirm a different value.
A8: Current TCT | B8: =NOW()-B6/24 -> 46306.261 | C8: Assumes your computer clock is on your local time zone.
A9: Current local time | B9: =NOW() -> 46305.97
A11: Summary
A12: Targets tracked | B12: =COUNTA('Mug Marks'!$B$5:$B$204) -> 1
A13: READY now | B13: =COUNTIF('Mug Marks'!$P$5:$P$204,"READY") -> 0
A14: On cooldown | B14: =COUNTIF('Mug Marks'!$P$5:$P$204,"Cooldown") -> 1
A15: Never hit | B15: =COUNTIF('Mug Marks'!$P$5:$P$204,"Never hit") -> 0
A16: Total logged attempts | B16: =COUNT('Mug Log'!$B$5:$B$1004) -> 1
A17: Total cash yield ($) | B17: =SUM('Mug Log'!$D$5:$D$1004) -> 2400000
A18: Average yield per attempt ($) | B18: =IF(B16=0,0,B17/B16) -> 2400000
A19: Yield, last 24h TCT ($) | B19: =SUMIFS('Mug Log'!$D$5:$D$1004,'Mug Log'!$A$5:$A$1004,">="&(B8-1)) -> 2400000
A21: Legend
A22: Blue text = input you type. Black text = formula (don't overwrite).
A23: Workflow: add a target on 'Mug Marks' (name + Torn ID), then log each attack on 'Mug Log'.
A24: Last Mug, Next Available, Status, Hits and Yield on 'Mug Marks' fill in automatically from the log.
A25: Rows marked EXAMPLE are placeholders - delete their contents when you start.

Sheet Hunting Guide
A1: Hunting Guide (condensed from MuggingMarks.txt)
A3: Pipeline | B3: How it works | C3: What to look for | D3: Trade-off / risk | E3: Confidence in source
A4: Buy-Mug (Pipeline 1) | B4: Buy a large stack of a liquid item from a seller, then attack immediately; your cash is now in their wallet. | C4: Xanax, Donator Packs, FHCs priced slightly below market. | D4: Victims may blacklist/enemy you or hire bounties. You also need the cash up front. | E4: Forum/anecdotal - unverified
A5: Casino Winner (Pipeline 1) | B5: Watch high-stakes Russian Roulette / poker; hit the winner right after a big payout. | C5: Fresh large wallet after a finished game. | D5: Timing is tight; winners may bank quickly. | E5: Anecdotal - unverified
A6: HoF Inactive (Pipeline 2) | B6: Filter the Networth Hall of Fame for high net worth, recently inactive players near your level. | C6: Net worth >$5B, inactive ~2-12 days (per source), high-income job (e.g. Brain Surgeon), high-tier property. | D6: Net worth is not cash on hand - much may be in assets. Verify wallet where possible. | E6: Reddit-sourced - unverified
A7: Overseas - Cayman / Switzerland (Pipeline 3) | B7: Fly in, check the local player list, hit targets as they land. | C7: Players carrying cash to bank (Cayman) or pay for treatment (Switzerland). | D7: Travel time and flight costs; targets may spend before you land. | E7: Facebook-group advice - unverified
A9: Caveats on the source notes
A10: 1. The 15-hour mug cooldown is treated as an assumption (Settings!B7). It is not confirmed by any Torn API/official reference provided - verify in-game before relying on it.
A11: 2. The source's HYPERLINK formula used "https://torn.com"&ID, which is not a valid profile URL. This workbook uses profiles.php?XID= and loader.php?sid=attack&user2ID= instead.
A12: 3. The source's one-cell DST formula is hard to maintain. This workbook uses a visible offset on Settings with an optional manual override.
A13: 4. 'Green or blue circle' as an activity signal is unverified; check the target's actual online/idle/offline indicator and last-action time.
A14: 5. Net worth and job income are indicators only - the wallet amount is what you actually get to mug.
A15: 6. Torn City Time is UTC. The sheet assumes your computer's clock is on your local zone for 'Current TCT'.
